serde_numpy-0.3.0.dist-info/METADATA
serde_numpy-0.3.0.dist-info/WHEEL
serde_numpy-0.3.0.dist-info/license_files/LICENSE
serde_numpy/__init__.py
serde_numpy/serde_numpy.cpython-37m-x86_64-linux-gnu.so
serde_numpy-0.3.0.dist-info/RECORD
