Metadata-Version: 2.1
Name: serde-numpy
Version: 0.3.0
Classifier: Development Status :: 5 - Production/Stable
Classifier: Intended Audience :: Developers
Classifier: License :: OSI Approved :: MIT License
Classifier: Operating System :: POSIX :: Linux
Classifier: Programming Language :: Python :: 3.7
Classifier: Programming Language :: Python :: 3.8
Classifier: Programming Language :: Python :: 3.9
Classifier: Programming Language :: Python :: 3.10
Classifier: Programming Language :: Python :: 3.11
Classifier: Programming Language :: Python :: Implementation :: CPython
Classifier: Programming Language :: Python
Classifier: Programming Language :: Rust
Classifier: Typing :: Typed
Requires-Dist: numpy >=1.18
License-File: LICENSE
Summary: A library for deserializing various formats directly into numpy arrays
Author: Will Norcliffe Brown
Requires-Python: >=3.7
Project-URL: homepage, https://github.com/wnorcbrown/serde-numpy
Project-URL: documentation, https://github.com/wnorcbrown/serde-numpy
Project-URL: repository, https://github.com/wnorcbrown/serde-numpy
